unkey/py/__init__.py
unkey/py/_hooks/__init__.py
unkey/py/_hooks/registration.py
unkey/py/_hooks/sdkhooks.py
unkey/py/_hooks/types.py
unkey/py/_version.py
unkey/py/analytics.py
unkey/py/apis.py
unkey/py/basesdk.py
unkey/py/errors/__init__.py
unkey/py/errors/apierror.py
unkey/py/errors/badrequesterrorresponse.py
unkey/py/errors/conflicterrorresponse.py
unkey/py/errors/forbiddenerrorresponse.py
unkey/py/errors/goneerrorresponse.py
unkey/py/errors/internalservererrorresponse.py
unkey/py/errors/no_response_error.py
unkey/py/errors/notfounderrorresponse.py
unkey/py/errors/preconditionfailederrorresponse.py
unkey/py/errors/responsevalidationerror.py
unkey/py/errors/serviceunavailableerrorresponse.py
unkey/py/errors/toomanyrequestserrorresponse.py
unkey/py/errors/unauthorizederrorresponse.py
unkey/py/errors/unkeyerror.py
unkey/py/errors/unprocessableentityerrorresponse.py
unkey/py/httpclient.py
unkey/py/identities.py
unkey/py/keys.py
unkey/py/models/__init__.py
unkey/py/models/badrequesterrordetails.py
unkey/py/models/baseerror.py
unkey/py/models/emptyresponse.py
unkey/py/models/identities_listidentitiesop.py
unkey/py/models/identity.py
unkey/py/models/keycreditsdata.py
unkey/py/models/keycreditsrefill.py
unkey/py/models/keyresponsedata.py
unkey/py/models/keysverifykeycredits.py
unkey/py/models/keysverifykeyratelimit.py
unkey/py/models/meta.py
unkey/py/models/pagination.py
unkey/py/models/permission.py
unkey/py/models/ratelimitoverride.py
unkey/py/models/ratelimitrequest.py
unkey/py/models/ratelimitresponse.py
unkey/py/models/role.py
unkey/py/models/security.py
unkey/py/models/updatekeycreditsdata.py
unkey/py/models/updatekeycreditsrefill.py
unkey/py/models/v2analyticsgetverificationsrequestbody.py
unkey/py/models/v2analyticsgetverificationsresponsebody.py
unkey/py/models/v2apiscreateapirequestbody.py
unkey/py/models/v2apiscreateapiresponsebody.py
unkey/py/models/v2apiscreateapiresponsedata.py
unkey/py/models/v2apisdeleteapirequestbody.py
unkey_py-2.6.0.dist-info/METADATA
unkey_py-2.6.0.dist-info/WHEEL
unkey_py-2.6.0.dist-info/RECORD
